binary_trader/__init__.py
binary_trader/binary_trader.py
version/__init__.py
version/version.py
tycoon_dev_trade-0.0.1.1.dist-info/METADATA
tycoon_dev_trade-0.0.1.1.dist-info/WHEEL
tycoon_dev_trade-0.0.1.1.dist-info/dependency_links.txt
tycoon_dev_trade-0.0.1.1.dist-info/top_level.txt
tycoon_dev_trade-0.0.1.1.dist-info/RECORD
