Metadata-Version: 2.1
Name: tycoon-dev-trade
Version: 0.0.1.1
Summary: Don't use it in a real account.
Home-page: UNKNOWN
Author: Baxromov
License: UNKNOWN
Platform: UNKNOWN
Classifier: Programming Language :: Python :: 3
Classifier: License :: OSI Approved :: MIT License
Classifier: Operating System :: OS Independent
Requires-Python: >=3.6
Requires-Dist: iqoptionapi
